CHANGES.txt
README.txt
setup.py
repoze/__init__.py
repoze.recipe.egg.egg-info/PKG-INFO
repoze.recipe.egg.egg-info/SOURCES.txt
repoze.recipe.egg.egg-info/dependency_links.txt
repoze.recipe.egg.egg-info/entry_points.txt
repoze.recipe.egg.egg-info/namespace_packages.txt
repoze.recipe.egg.egg-info/not-zip-safe
repoze.recipe.egg.egg-info/requires.txt
repoze.recipe.egg.egg-info/top_level.txt
repoze/recipe/__init__.py
repoze/recipe/egg/README.txt
repoze/recipe/egg/__init__.py
repoze/recipe/egg/api.txt
repoze/recipe/egg/custom.py
repoze/recipe/egg/custom.txt
repoze/recipe/egg/egg.py
repoze/recipe/egg/selecting-python.txt
repoze/recipe/egg/tests.py