Metadata-Version: 1.0
Name: repoze.recipe.egg
Version: 0.1
Summary: Recipe for installing Python package distributions as eggs
Home-page: http://dist.repoze.org/simple/repoze.recipe.egg
Author: Jim Fulton (forked by Chris McDonough)
Author-email: chrism@plope.com
License: ZPL 2.1
Keywords: development build
Platform: UNKNOWN
Classifier: Development Status :: 5 - Production/Stable
Classifier: Framework :: Buildout
Classifier: Intended Audience :: Developers
Classifier: License :: OSI Approved :: Zope Public License
Classifier: Topic :: Software Development :: Build Tools
Classifier: Topic :: Software Development :: Libraries :: Python Modules
